flamapy_dev.py
commands/__init__.py
commands/make.py
commands/packages.py
commands/repositories.py
commands/versions.py
flamapy_dev-0.0.2.dist-info/METADATA
flamapy_dev-0.0.2.dist-info/WHEEL
flamapy_dev-0.0.2.dist-info/entry_points.txt
flamapy_dev-0.0.2.dist-info/top_level.txt
flamapy_dev-0.0.2.dist-info/RECORD
