Metadata-Version: 2.1
Name: flamapy-dev
Version: 0.0.2
Summary: CLI tool for managing Git repositories and Python packages for the Flamapy distribution
Home-page: UNKNOWN
Author: José A. Galindo
Author-email: jagalindo@us.es
License: UNKNOWN
Platform: UNKNOWN
Requires-Python: >=3.6
Requires-Dist: click
Requires-Dist: bump-my-version==1.2.0
Requires-Dist: pytest
Requires-Dist: ruff
Requires-Dist: mypy
Requires-Dist: packaging
Requires-Dist: build
Requires-Dist: setuptools
Requires-Dist: wheel
